ntk/__init__.py
ntk/__main__.py
ntk/command.py
ntk/conf.py
ntk/decorator.py
ntk/gateway.py
ntk/installer.py
ntk/ntk_parser.py
ntk/utils.py
tests/__init__.py
tests/test_command.py
tests/test_config.py
tests/test_gateway.py
tests/test_installer.py
next_theme_kit-1.0.7.dist-info/LICENSE
next_theme_kit-1.0.7.dist-info/METADATA
next_theme_kit-1.0.7.dist-info/WHEEL
next_theme_kit-1.0.7.dist-info/entry_points.txt
next_theme_kit-1.0.7.dist-info/top_level.txt
next_theme_kit-1.0.7.dist-info/RECORD
