Metadata-Version: 2.1
Name: next-theme-kit
Version: 1.0.7
Summary: UNKNOWN
Home-page: https://github.com/29next/theme-kit
Author: 29next
Author-email: dev@29next.com
License: UNKNOWN
Platform: UNKNOWN
Requires-Python: >=3.8
License-File: LICENSE
Requires-Dist: PyYAML>=5.4
Requires-Dist: requests>=2.25
Requires-Dist: watchgod>=0.7
Requires-Dist: libsass>=0.21.0
